folx/__init__.py
folx/ad.py
folx/api.py
folx/custom_hessian.py
folx/hessian.py
folx/interpreter.py
folx/jvp.py
folx/operators.py
folx/tree_utils.py
folx/utils.py
folx/vmap.py
folx/wrapped_functions.py
folx/wrapper.py
folx/experimental/__init__.py
folx/experimental/vmap.py
folx/experimental/pallas/attention/__init__.py
folx/experimental/pallas/attention/custom_gradients.py
folx/experimental/pallas/attention/forward_laplacian.py
folx/experimental/pallas/attention/mhsa.py
folx/experimental/pallas/attention/mhsea.py
folx/experimental/pallas/attention/utils.py
folx-0.2.19.dist-info/METADATA
folx-0.2.19.dist-info/WHEEL
folx-0.2.19.dist-info/licenses/LICENSE
folx-0.2.19.dist-info/RECORD
