Metadata-Version: 2.4
Name: folx
Version: 0.2.19
Summary: Forward Laplacian for JAX
Project-URL: Homepage, https://github.com/microsoft/folx
Project-URL: Repository, https://github.com/microsoft/folx
Author-email: Nicholas Gao <n.gao@tum.de>, Jonas Koehler <jonas.koehler@microsoft.com>, Adam Foster <adam.e.foster@microsoft.com>
Maintainer-email: Nicholas Gao <n.gao@tum.de>
License-Expression: MIT
License-File: LICENSE
Keywords: jax,laplacian,numeric
Classifier: Development Status :: 4 - Beta
Classifier: Environment :: Console
Classifier: Environment :: GPU :: NVIDIA CUDA
Classifier: Intended Audience :: Science/Research
Classifier: Operating System :: MacOS :: MacOS X
Classifier: Operating System :: POSIX :: Linux
Classifier: Programming Language :: Python :: 3.11
Classifier: Programming Language :: Python :: 3.12
Classifier: Topic :: Scientific/Engineering :: Artificial Intelligence
Classifier: Topic :: Scientific/Engineering :: Chemistry
Classifier: Topic :: Scientific/Engineering :: Physics
Requires-Python: <4.0,>=3.10
Requires-Dist: jax>=0.4.10; python_version < '3.13'
Requires-Dist: jax>=0.4.34; python_version >= '3.13'
Requires-Dist: jaxtyping>=0.2.36
Requires-Dist: numpy>=1.25; python_version < '3.13'
Requires-Dist: numpy>=2.1; python_version >= '3.13'
